tradesys/__init__.py
tradesys/lib/__init__.py
tradesys/lib/brokers/XTB.py
tradesys/lib/brokers/__init__.py
tradesys/lib/connectors/__init__.py
tradesys/lib/credentials/__init__.py
tradesys/lib/credentials/loaders.py
tradesys/lib/errors/__init__.py
tradesys/lib/interfaces/IBroker.py
tradesys/lib/interfaces/IEventHandler.py
tradesys/lib/interfaces/ILoader.py
tradesys/lib/interfaces/__init__.py
tradesys/lib/types/__init__.py
tradesys/lib/types/constants.py
tradesys_lib-0.0.2.dev3.dist-info/LICENSE
tradesys_lib-0.0.2.dev3.dist-info/METADATA
tradesys_lib-0.0.2.dev3.dist-info/WHEEL
tradesys_lib-0.0.2.dev3.dist-info/top_level.txt
tradesys_lib-0.0.2.dev3.dist-info/RECORD
